comvex/__init__.py
comvex/version.py
comvex/aft/__init__.py
comvex/aft/config.py
comvex/aft/model.py
comvex/botnet/__init__.py
comvex/botnet/config.py
comvex/botnet/model.py
comvex/cait/__init__.py
comvex/cait/config.py
comvex/cait/model.py
comvex/coat/__init__.py
comvex/coat/config.py
comvex/coat/model.py
comvex/coatnet/__init__.py
comvex/coatnet/config.py
comvex/coatnet/model.py
comvex/convit/__init__.py
comvex/convit/config.py
comvex/convit/model.py
comvex/efficientdet/__init__.py
comvex/efficientdet/config.py
comvex/efficientdet/model.py
comvex/efficientnet_v2/__init__.py
comvex/efficientnet_v2/config.py
comvex/efficientnet_v2/model.py
comvex/efficientnet_v2/progressive_learning.py
comvex/fnet/__init__.py
comvex/fnet/config.py
comvex/fnet/model.py
comvex/g_mlp/__init__.py
comvex/g_mlp/config.py
comvex/g_mlp/model.py
comvex/mlpmixer/__init__.py
comvex/mlpmixer/config.py
comvex/mlpmixer/model.py
comvex/perceiver/__init__.py
comvex/perceiver/model.py
comvex/resmlp/__init__.py
comvex/resmlp/config.py
comvex/resmlp/model.py
comvex/set_transformer/__init__.py
comvex/set_transformer/model.py
comvex/swin_transformer/__init__.py
comvex/swin_transformer/config.py
comvex/swin_transformer/model.py
comvex/transformer/__init__.py
comvex/transformer/model.py
comvex/transunet/__init__.py
comvex/transunet/model.py
comvex/transunet/utils.py
comvex/utils/__init__.py
comvex/utils/base_block.py
comvex/utils/bifpn.py
comvex/utils/config_base.py
comvex/utils/convolution.py
comvex/utils/dropout.py
comvex/utils/layer_scale.py
comvex/utils/multihead_attention.py
comvex/utils/position_encodings.py
comvex/utils/unet.py
comvex/utils/efficientnet/__init__.py
comvex/utils/efficientnet/config.py
comvex/utils/efficientnet/model.py
comvex/utils/helpers/__init__.py
comvex/utils/helpers/classes.py
comvex/utils/helpers/functions.py
comvex/utils/mixup/__init__.py
comvex/utils/mixup/mixup.py
comvex/utils/rand_augment/__init__.py
comvex/utils/rand_augment/config.py
comvex-0.4.0.dist-info/LICENSE
comvex-0.4.0.dist-info/METADATA
comvex-0.4.0.dist-info/WHEEL
comvex-0.4.0.dist-info/top_level.txt
comvex-0.4.0.dist-info/RECORD
