Metadata-Version: 2.1
Name: comvex
Version: 0.4.0
Summary: Implementations of Recent Papers in Computer Vision
Home-page: https://github.com/blakechi/ComVEX
Author: Blake Chi
Author-email: blakechi.chiaohu@gmail.com
License: UNKNOWN
Keywords: pytorch einops computer-vision
Platform: UNKNOWN
Classifier: Development Status :: 3 - Alpha
Classifier: License :: OSI Approved :: Apache Software License
Classifier: Topic :: Scientific/Engineering :: Artificial Intelligence
Classifier: Topic :: Software Development :: Libraries :: Python Modules
Classifier: Intended Audience :: Developers
Classifier: Intended Audience :: Science/Research
Classifier: Programming Language :: Python :: 3.6
Classifier: Programming Language :: Python :: 3.7
Classifier: Programming Language :: Python :: 3.8
Classifier: Programming Language :: Python :: 3.9
Requires-Python: >=3.6
License-File: LICENSE
Requires-Dist: torch (>=1.8.1)
Requires-Dist: einops (>=0.3.0)
Requires-Dist: torchvision (>=0.8.2)
